setup.cfg
setup.py
polygonmeshtools/__init__.py
polygonmeshtools/calc.py
polygonmeshtools/check_pep8.py
polygonmeshtools/coords.py
polygonmeshtools/plot.py
polygonmeshtools/plot_original.py
polygonmeshtools/test_basic_understanding.py
polygonmeshtools/test_calc.py
polygonmeshtools/test_coords.py
polygonmeshtools/test_plot.py
polygonmeshtools.egg-info/PKG-INFO
polygonmeshtools.egg-info/SOURCES.txt
polygonmeshtools.egg-info/dependency_links.txt
polygonmeshtools.egg-info/top_level.txt