Metadata-Version: 1.0
Name: polygonmeshtools
Version: 0.46
Summary: A package for creating polygon-shaped geometries         from cuboidal finite difference elements
Home-page: https://bitbucket.org/fangohr/polygon-finite-difference-mesh-tools/get/tip.tar.gz
Author: Xander Marjoram
Author-email: am31g12@soton.ac.uk
License: UNKNOWN
Keywords: polygon,mesh,geometry,finite,difference,fidimag
Platform: UNKNOWN
